MANIFEST.in
README.rst
requirements-dev.txt
requirements.txt
setup.cfg
setup.py
pySparkUtils/SVD.py
pySparkUtils/__init__.py
pySparkUtils/utils.py
pySparkUtils.egg-info/PKG-INFO
pySparkUtils.egg-info/SOURCES.txt
pySparkUtils.egg-info/dependency_links.txt
pySparkUtils.egg-info/requires.txt
pySparkUtils.egg-info/top_level.txt
test/test_change.py
test/test_executor_ips.py
test/test_fallback.py
test/test_rdd_pickle.py
test/test_regroup.py
test/test_repartition.py
test/test_svd.py
test/test_thunder_wrapper.py