Metadata-Version: 1.1
Name: pySparkUtils
Version: 0.2.5
Summary: A collection of utilities for handling pySpark's SparkContext
Home-page: https://github.com/boazmohar/pySparkUtils
Author: Boaz Mohar
Author-email: boazmohar@gmail.com
License: MIT
Download-URL: https://github.com/boazmohar/pySparkUtils/archive/0.2.5.tar.gz
Keywords: spark,pyspark
Platform: UNKNOWN
Classifier: Development Status :: 3 - Alpha
Classifier: License :: OSI Approved :: MIT License
Classifier: Programming Language :: Python :: 2
Classifier: Programming Language :: Python :: 2.7
Classifier: Programming Language :: Python :: 3
Classifier: Programming Language :: Python :: 3.5
